hydra_youtube_api/__init__.py
hydra_youtube_api/cli.py
hydra_youtube_api/sources.py
hydra_youtube_api/youtube.py
hydra_youtube_api-1.1.5.dist-info/METADATA
hydra_youtube_api-1.1.5.dist-info/WHEEL
hydra_youtube_api-1.1.5.dist-info/entry_points.txt
hydra_youtube_api-1.1.5.dist-info/top_level.txt
hydra_youtube_api-1.1.5.dist-info/RECORD
