Metadata-Version: 2.1
Name: hydra_youtube_api
Version: 1.1.5
Summary: Fast and simple API for YouTube and YouTube Music
Home-page: https://github.com/Hydralerne/youtube-api
Author: Hydra de lerne
Author-email: hydra@onvo.me
License: AGPL-3.0
Keywords: youtube,music,api,metadata,downloader
Classifier: Programming Language :: Python :: 3
Classifier: License :: OSI Approved :: GNU Affero General Public License v3
Classifier: Operating System :: OS Independent
Requires-Python: >=3.6
Requires-Dist: requests
Requires-Dist: aiohttp
